FunPayPy/__init__.py
FunPayPy/account.py
FunPayPy/types.py
FunPayPy/common/__init__.py
FunPayPy/common/enums.py
FunPayPy/common/exceptions.py
FunPayPy/common/utils.py
FunPayPy/updater/__init__.py
FunPayPy/updater/events.py
FunPayPy/updater/runner.py
FunPayPython-1.1.1.dist-info/METADATA
FunPayPython-1.1.1.dist-info/WHEEL
FunPayPython-1.1.1.dist-info/top_level.txt
FunPayPython-1.1.1.dist-info/RECORD
