Metadata-Version: 2.1
Name: FunPayPython
Version: 1.1.1
Summary: Прослойка между FunPayAPI и клиентом. [Исправленная версия]
Home-page: https://discord.gg/HNhrWJKz3T
Author: ArttekPublic
Author-email: arttekpublic@mail.ru
License: GPL3
Keywords: funpay bot api tools
Classifier: Development Status :: 5 - Production/Stable
Classifier: Programming Language :: Python :: 3
Classifier: Environment :: Console
Classifier: License :: OSI Approved :: GNU General Public License v3 (GPLv3)
Requires-Dist: requests ==2.28.1
Requires-Dist: beautifulsoup4
Requires-Dist: requests-toolbelt ==0.10.1
